LICENSE
README.md
setup.py
poisonapple/__init__.py
poisonapple/cli.py
poisonapple/techniques.py
poisonapple/util.py
poisonapple.egg-info/PKG-INFO
poisonapple.egg-info/SOURCES.txt
poisonapple.egg-info/dependency_links.txt
poisonapple.egg-info/entry_points.txt
poisonapple.egg-info/requires.txt
poisonapple.egg-info/top_level.txt
poisonapple/auxiliary/login-items-add.sh
poisonapple/auxiliary/login-items-rm.sh
poisonapple/auxiliary/poisonapple.plist
poisonapple/auxiliary/poisonapple.sh