Metadata-Version: 2.1
Name: poisonapple
Version: 0.2.3
Summary: Command-line tool to perform various persistence mechanism techniques on macOS.
Home-page: https://github.com/CyborgSecurity/PoisonApple
Author: Austin Jackson
Author-email: vesche@protonmail.com
License: MIT
Platform: UNKNOWN
Classifier: Development Status :: 4 - Beta
Classifier: Environment :: Console
Classifier: Intended Audience :: Information Technology
Classifier: License :: OSI Approved :: MIT License
Classifier: Programming Language :: Python :: 3
Classifier: Programming Language :: Python :: 3.9
Classifier: Topic :: Security
License-File: LICENSE
